file_io_cli.py
file.io_cli-1.0.4.dist-info/LICENSE.txt
file.io_cli-1.0.4.dist-info/METADATA
file.io_cli-1.0.4.dist-info/WHEEL
file.io_cli-1.0.4.dist-info/entry_points.txt
file.io_cli-1.0.4.dist-info/top_level.txt
file.io_cli-1.0.4.dist-info/zip-safe
file.io_cli-1.0.4.dist-info/RECORD
