Metadata-Version: 2.1
Name: file.io-cli
Version: 1.0.4
Summary: Command-line tool to upload files to https://file.io
Home-page: https://github.com/NiklasRosenstein/file.io-cli
Author: Niklas Rosenstein
Author-email: rosensteinniklas@gmail.com
License: UNKNOWN
Platform: UNKNOWN
Requires-Python: >=3.3.0,<4.0.0
Requires-Dist: clipboard (<1.0.0,>=0.0.4)
Requires-Dist: requests (<3.0.0,>=2.25.1)
